nonebot_plugin_qrcode2/__init__.py
nonebot_plugin_qrcode2/config.py
nonebot_plugin_qrcode2/decode.py
nonebot_plugin_qrcode2/exception.py
nonebot_plugin_qrcode2/resource/wechat_model/detect.caffemodel
nonebot_plugin_qrcode2/resource/wechat_model/detect.prototxt
nonebot_plugin_qrcode2/resource/wechat_model/sr.caffemodel
nonebot_plugin_qrcode2/resource/wechat_model/sr.prototxt
nonebot_plugin_qrcode2-0.2.3.dist-info/LICENSE
nonebot_plugin_qrcode2-0.2.3.dist-info/METADATA
nonebot_plugin_qrcode2-0.2.3.dist-info/WHEEL
nonebot_plugin_qrcode2-0.2.3.dist-info/RECORD
