Metadata-Version: 2.1
Name: nonebot-plugin-qrcode2
Version: 0.2.3
Summary: 本地解析二维码
Home-page: https://github.com/tomorinao-www/nonebot-plugin-qrcode2
License: MIT
Author: 友利奈绪-勿忘我
Author-email: 1520872279@qq.com
Requires-Python: >=3.10
Classifier: License :: OSI Approved :: MIT License
Classifier: Programming Language :: Python :: 3
Classifier: Programming Language :: Python :: 3.10
Classifier: Programming Language :: Python :: 3.11
Requires-Dist: httpx (>=0.24.1)
Requires-Dist: nonebot-adapter-onebot (>=2.2.3)
Requires-Dist: nonebot2 (>=2.2.0,<3.0.0)
Requires-Dist: numpy (>=1.23.5)
Requires-Dist: opencv-contrib-python (>=4.8.0.76)
Requires-Dist: opencv-python (>=4.7.0.68)
Requires-Dist: pillow (>=9.5.0)
Requires-Dist: pyzbar (>=0.1.9)
Project-URL: Documentation, https://github.com/tomorinao-www/nonebot-plugin-qrcode2#README.md
Project-URL: Repository, https://github.com/tomorinao-www/nonebot-plugin-qrcode2
